<rdf:RDF xmlns:brick="https://brickschema.org/schema/Brick#" xmlns:csvw="http://www.w3.org/ns/csvw#" xmlns:dc="http://purl.org/dc/elements/1.1/" xmlns:dcat="http://www.w3.org/ns/dcat#" xmlns:dcmitype="http://purl.org/dc/dcmitype/" xmlns:dcterms="http://purl.org/dc/terms/" xmlns:dcam="http://purl.org/dc/dcam/" xmlns:doap="http://usefulinc.com/ns/doap#" xmlns:foaf="http://xmlns.com/foaf/0.1/" xmlns:odrl="http://www.w3.org/ns/odrl/2/" xmlns:org="http://www.w3.org/ns/org#" xmlns:owl="http://www.w3.org/2002/07/owl#" xmlns:prof="http://www.w3.org/ns/dx/prof/" xmlns:prov="http://www.w3.org/ns/prov#" xmlns:qb="http://purl.org/linked-data/cube#" xmlns:rdf="http://www.w3.org/1999/02/22-rdf-syntax-ns#" xmlns:rdfs="http://www.w3.org/2000/01/rdf-schema#" xmlns:schema="https://schema.org/" xmlns:sh="http://www.w3.org/ns/shacl#" xmlns:skos="http://www.w3.org/2004/02/skos/core#" xmlns:sosa="http://www.w3.org/ns/sosa/" xmlns:ssn="http://www.w3.org/ns/ssn/" xmlns:time="http://www.w3.org/2006/time#" xmlns:vann="http://purl.org/vocab/vann/" xmlns:void="http://rdfs.org/ns/void#" xmlns:xsd="http://www.w3.org/2001/XMLSchema#" xmlns:gbConv="http://sbols.org/genBankConversion#" xmlns:sbol="http://sbols.org/v2#" xmlns:genbank="http://www.ncbi.nlm.nih.gov/genbank#" xmlns:obo="http://purl.obolibrary.org/obo/" xmlns:om="http://www.ontology-of-units-of-measure.org/resource/om-2/" xmlns:addgene="https://www.addgene.org/">
  <sbol:ComponentDefinition rdf:about="www.examples.org/Exported">
    <sbol:type rdf:resource="http://identifiers.org/so/SO:0000987"/>
    <addgene:fiveSequencingPrimer>TAATACGACTCACTATAGGG</addgene:fiveSequencingPrimer>
    <addgene:cloningMethod>Restriction Enzyme</addgene:cloningMethod>
    <sbol:sequence rdf:resource="www.examples.org/Exported_seq"/>
    <addgene:growthTemperature>37&#176;C</addgene:growthTemperature>
    <genbank:keywords>pmCherry-miR-Let7a</genbank:keywords>
    <addgene:vectorType>Mammalian Expression</addgene:vectorType>
    <sbol:type rdf:resource="http://www.biopax.org/release/biopax-level3.owl#DnaRegion"/>
    <addgene:doi rdf:resource="https://www.ncbi.nlm.nih.gov/pubmed/23042294"/>
    <addgene:depositingLab rdf:resource="https://www.addgene.org/browse/pi/1931/"/>
    <addgene:refMethod> pmCherry-miR-Let7a was a gift from  Scott Oakes   (Addgene plasmid # 53101)   </addgene:refMethod>
    <addgene:industryTerms>Not Available to Industry</addgene:industryTerms>
    <addgene:bacterialResistances>Ampicillin</addgene:bacterialResistances>
    <genbank:division>SYN</genbank:division>
    <dcterms:description>mCherry reporter for Let7a.</dcterms:description>
    <genbank:reference rdf:resource="www.examples.org/Exported/reference1"/>
    <addgene:growthStrains>DH5alpha</addgene:growthStrains>
    <sbol:persistentIdentity rdf:resource="www.examples.org/Exported"/>
    <addgene:geneInsertName>mCherry ORF plus tandem miR-Let7a binding sites</addgene:geneInsertName>
    <genbank:molecule>ds-DNA</genbank:molecule>
    <addgene:refBib>  IRE1alpha cleaves select microRNAs during ER stress to derepress translation of proapoptotic Caspase-2. Upton JP, Wang L, Han D, Wang ES, Huskey NE, Lim L, Truitt M, McManus MT, Ruggero D, Goga A, Papa FR, Oakes SA. Science. 2012 Nov 9;338(6108):818-22. doi: 10.1126/science.1226191. Epub 2012 Oct 4. 10.1126/science.1226191   PubMed 23042294   </addgene:refBib>
    <addgene:selectableMarkers>Puromycin</addgene:selectableMarkers>
    <addgene:academicNonprofitTerms>UBMTA
Takara Bio Limited Use Label License (formerly Clontech)</addgene:academicNonprofitTerms>
    <sbol:role rdf:resource="http://identifiers.org/so/SO:0002206"/>
    <addgene:copyNumber>High Copy</addgene:copyNumber>
    <addgene:promoter>EF1a</addgene:promoter>
    <addgene:purpose>mCherry reporter for Let7a</addgene:purpose>
    <obo:OBI_0001617>23042294</obo:OBI_0001617>
    <addgene:vectorBackbone>pSicoR-EPMT</addgene:vectorBackbone>
    <genbank:source>synthetic DNA construct</genbank:source>
    <genbank:organism>synthetic DNA construct</genbank:organism>
    <addgene:plasmidTitle>pmCherry-miR-Let7a</addgene:plasmidTitle>
    <addgene:fiveCloningSite>AscI
    (not destroyed)</addgene:fiveCloningSite>
    <sbol:displayId>Exported</sbol:displayId>
    <genbank:reference rdf:resource="www.examples.org/Exported/reference0"/>
    <genbank:date>03-SEP-2021</genbank:date>
    <addgene:threeCloningSite>PacI
    (not destroyed)</addgene:threeCloningSite>
    <addgene:addgeneId>53101</addgene:addgeneId>
    <sbol:sequenceAnnotation>
      <sbol:SequenceAnnotation rdf:about="www.examples.org/Exported/annotation0">
        <gbConv:mol_type>other DNA</gbConv:mol_type>
        <gbConv:organism>synthetic DNA construct</gbConv:organism>
        <sbol:role rdf:resource="http://identifiers.org/so/SO:0002206"/>
        <sbol:persistentIdentity rdf:resource="www.examples.org/Exported/annotation0"/>
        <sbol:location>
          <sbol:Range rdf:about="www.examples.org/Exported/annotation0/range">
            <sbol:orientation rdf:resource="http://sbols.org/v2#inline"/>
            <sbol:end>66</sbol:end>
            <sbol:displayId>range</sbol:displayId>
            <sbol:start>1</sbol:start>
            <sbol:persistentIdentity rdf:resource="www.examples.org/Exported/annotation0/range"/>
          </sbol:Range>
        </sbol:location>
        <dcterms:title>synthetic DNA construct</dcterms:title>
        <sbol:displayId>annotation0</sbol:displayId>
      </sbol:SequenceAnnotation>
    </sbol:sequenceAnnotation>
    <genbank:locus>Exported</genbank:locus>
  </sbol:ComponentDefinition>
  <genbank:Reference rdf:about="www.examples.org/Exported/reference0">
    <genbank:pubmed>23042294</genbank:pubmed>
    <genbank:journal>Science. 2012 Nov 9;338(6108):818-22. doi: 10.1126/science.1226191. Epub 2012 Oct 4.</genbank:journal>
    <genbank:title>IRE1alpha cleaves select microRNAs during ER stress to derepress translation of proapoptotic Caspase-2.</genbank:title>
    <genbank:label>1  (bases 1 to 66)</genbank:label>
    <genbank:authors>Upton JP, Wang L, Han D, Wang ES, Huskey NE, Lim L, Truitt M, McManus MT, Ruggero D, Goga A, Papa FR, Oakes SA</genbank:authors>
  </genbank:Reference>
  <genbank:Reference rdf:about="www.examples.org/Exported/reference1">
    <genbank:journal>Exported Sep 3, 2021 from SnapGene Server 1.1.58 http://www.snapgene.com</genbank:journal>
    <genbank:authors>.</genbank:authors>
    <genbank:label>2  (bases 1 to 66)</genbank:label>
    <genbank:title>Direct Submission</genbank:title>
  </genbank:Reference>
  <sbol:Sequence rdf:about="www.examples.org/Exported_seq">
    <sbol:persistentIdentity rdf:resource="www.examples.org/Exported_seq"/>
    <sbol:encoding rdf:resource="http://www.chem.qmul.ac.uk/iubmb/misc/naseq.html"/>
    <sbol:displayId>Exported_seq</sbol:displayId>
    <sbol:elements>ggcgcgccaactatacaacctactacctcagcatgcaactatacaacctactacctcattaattaa</sbol:elements>
  </sbol:Sequence>
</rdf:RDF>
