<rdf:RDF xmlns:brick="https://brickschema.org/schema/Brick#" xmlns:csvw="http://www.w3.org/ns/csvw#" xmlns:dc="http://purl.org/dc/elements/1.1/" xmlns:dcat="http://www.w3.org/ns/dcat#" xmlns:dcmitype="http://purl.org/dc/dcmitype/" xmlns:dcterms="http://purl.org/dc/terms/" xmlns:dcam="http://purl.org/dc/dcam/" xmlns:doap="http://usefulinc.com/ns/doap#" xmlns:foaf="http://xmlns.com/foaf/0.1/" xmlns:odrl="http://www.w3.org/ns/odrl/2/" xmlns:org="http://www.w3.org/ns/org#" xmlns:owl="http://www.w3.org/2002/07/owl#" xmlns:prof="http://www.w3.org/ns/dx/prof/" xmlns:prov="http://www.w3.org/ns/prov#" xmlns:qb="http://purl.org/linked-data/cube#" xmlns:rdf="http://www.w3.org/1999/02/22-rdf-syntax-ns#" xmlns:rdfs="http://www.w3.org/2000/01/rdf-schema#" xmlns:schema="https://schema.org/" xmlns:sh="http://www.w3.org/ns/shacl#" xmlns:skos="http://www.w3.org/2004/02/skos/core#" xmlns:sosa="http://www.w3.org/ns/sosa/" xmlns:ssn="http://www.w3.org/ns/ssn/" xmlns:time="http://www.w3.org/2006/time#" xmlns:vann="http://purl.org/vocab/vann/" xmlns:void="http://rdfs.org/ns/void#" xmlns:xsd="http://www.w3.org/2001/XMLSchema#" xmlns:gbConv="http://sbols.org/genBankConversion#" xmlns:sbol="http://sbols.org/v2#" xmlns:genbank="http://www.ncbi.nlm.nih.gov/genbank#" xmlns:obo="http://purl.obolibrary.org/obo/" xmlns:om="http://www.ontology-of-units-of-measure.org/resource/om-2/" xmlns:addgene="https://www.addgene.org/">
  <sbol:ComponentDefinition rdf:about="www.examples.org/Exported">
    <addgene:refBib>  A genetic cell context-dependent role for ZEB1 in lung cancer. Zhang T, Guo L, Creighton CJ, Lu Q, Gibbons DL, Yi ES, Deng B, Molina JR, Sun Z, Yang P, Yang Y. Nat Commun. 2016 Jul 26;7:12231. doi: 10.1038/ncomms12231. 10.1038/ncomms12231   PubMed 27456471   </addgene:refBib>
    <sbol:displayId>Exported</sbol:displayId>
    <sbol:type rdf:resource="http://identifiers.org/so/SO:0000987"/>
    <dcterms:description>Renilla Luciferase reporter assay for RANBP9 3'UTR with mutations on miR-200c binding site.</dcterms:description>
    <sbol:sequence rdf:resource="www.examples.org/Exported_seq"/>
    <genbank:keywords>pCIneoRL-RanBP93'UTR-mir200c-mut</genbank:keywords>
    <addgene:threeCloningSite>Not1
    (not destroyed)</addgene:threeCloningSite>
    <addgene:copyNumber>High Copy</addgene:copyNumber>
    <addgene:growthStrains>DH5alpha</addgene:growthStrains>
    <addgene:promoter>CMV</addgene:promoter>
    <addgene:fiveCloningSite>Xba1
    (not destroyed)</addgene:fiveCloningSite>
    <addgene:bacterialResistances>Ampicillin</addgene:bacterialResistances>
    <genbank:molecule>ds-DNA</genbank:molecule>
    <sbol:sequenceAnnotation>
      <sbol:SequenceAnnotation rdf:about="www.examples.org/Exported/annotation0">
        <sbol:location>
          <sbol:Range rdf:about="www.examples.org/Exported/annotation0/range">
            <sbol:orientation rdf:resource="http://sbols.org/v2#inline"/>
            <sbol:displayId>range</sbol:displayId>
            <sbol:persistentIdentity rdf:resource="www.examples.org/Exported/annotation0/range"/>
            <sbol:start>1</sbol:start>
            <sbol:end>803</sbol:end>
          </sbol:Range>
        </sbol:location>
        <sbol:displayId>annotation0</sbol:displayId>
        <gbConv:mol_type>other DNA</gbConv:mol_type>
        <sbol:role rdf:resource="http://identifiers.org/so/SO:0002206"/>
        <sbol:persistentIdentity rdf:resource="www.examples.org/Exported/annotation0"/>
        <gbConv:organism>synthetic DNA construct</gbConv:organism>
        <dcterms:title>synthetic DNA construct</dcterms:title>
      </sbol:SequenceAnnotation>
    </sbol:sequenceAnnotation>
    <addgene:vectorBackbone>pCIneoRL</addgene:vectorBackbone>
    <genbank:locus>Exported</genbank:locus>
    <sbol:type rdf:resource="http://www.biopax.org/release/biopax-level3.owl#DnaRegion"/>
    <genbank:date>12-JUN-2021</genbank:date>
    <genbank:reference rdf:resource="www.examples.org/Exported/reference1"/>
    <genbank:source>synthetic DNA construct</genbank:source>
    <sbol:role rdf:resource="http://identifiers.org/so/SO:0002206"/>
    <addgene:refMethod> pCIneoRL-RanBP93'UTR-mir200c-mut was a gift from  Yanan Yang    (Addgene plasmid # 84592 ; http://n2t.net/addgene:84592 ; RRID:Addgene_84592)    </addgene:refMethod>
    <addgene:backboneSizeWoInsertBp>6380</addgene:backboneSizeWoInsertBp>
    <addgene:geneInsertName>RANBP9 3'UTR</addgene:geneInsertName>
    <addgene:vectorType>Luciferase</addgene:vectorType>
    <addgene:industryTerms>Not Available to Industry</addgene:industryTerms>
    <addgene:purpose>Renilla Luciferase reporter assay for RANBP9 3'UTR with mutations on miR-200c binding site</addgene:purpose>
    <addgene:tagFusionProtein>Renilla Luciferase (N terminal on backbone)</addgene:tagFusionProtein>
    <addgene:depositingLab rdf:resource="https://www.addgene.org/browse/pi/3104/"/>
    <addgene:academicNonprofitTerms>UBMTA</addgene:academicNonprofitTerms>
    <addgene:species>H. sapiens (human)</addgene:species>
    <addgene:cloningMethod>Restriction Enzyme</addgene:cloningMethod>
    <genbank:division>SYN</genbank:division>
    <genbank:organism>synthetic DNA construct</genbank:organism>
    <obo:OBI_0001617>27456471</obo:OBI_0001617>
    <addgene:insertSizeBp>885</addgene:insertSizeBp>
    <addgene:growthTemperature>37&#176;C</addgene:growthTemperature>
    <addgene:doi rdf:resource="https://www.ncbi.nlm.nih.gov/pubmed/27456471"/>
    <sbol:persistentIdentity rdf:resource="www.examples.org/Exported"/>
    <addgene:threeSequencingPrimer>EBV-rev</addgene:threeSequencingPrimer>
    <genbank:reference rdf:resource="www.examples.org/Exported/reference0"/>
    <addgene:fiveSequencingPrimer>RenLuc3F</addgene:fiveSequencingPrimer>
    <addgene:mutation>on miR-200c binding site on RANBP9 3'UTR</addgene:mutation>
    <addgene:plasmidTitle>pCIneoRL-RanBP93'UTR-mir200c-mut</addgene:plasmidTitle>
    <addgene:addgeneId>84592</addgene:addgeneId>
  </sbol:ComponentDefinition>
  <genbank:Reference rdf:about="www.examples.org/Exported/reference0">
    <genbank:title>A genetic cell context-dependent role for ZEB1 in lung cancer.</genbank:title>
    <genbank:authors>Zhang T, Guo L, Creighton CJ, Lu Q, Gibbons DL, Yi ES, Deng B, Molina JR, Sun Z, Yang P, Yang Y</genbank:authors>
    <genbank:journal>Nat Commun. 2016 Jul 26;7:12231. doi: 10.1038/ncomms12231.</genbank:journal>
    <genbank:pubmed>27456471</genbank:pubmed>
    <genbank:label>1  (bases 1 to 803)</genbank:label>
  </genbank:Reference>
  <genbank:Reference rdf:about="www.examples.org/Exported/reference1">
    <genbank:journal>Exported Jun 12, 2021 from SnapGene Server 1.1.58 http://www.snapgene.com</genbank:journal>
    <genbank:label>2  (bases 1 to 803)</genbank:label>
    <genbank:title>Direct Submission</genbank:title>
    <genbank:authors>.</genbank:authors>
  </genbank:Reference>
  <sbol:Sequence rdf:about="www.examples.org/Exported_seq">
    <sbol:encoding rdf:resource="http://www.chem.qmul.ac.uk/iubmb/misc/naseq.html"/>
    <sbol:persistentIdentity rdf:resource="www.examples.org/Exported_seq"/>
    <sbol:elements>attctagaccacagtggaagactacctacattagctacgcatttcaagagctcacacttatattgtggcatatagtcaacatggaagtagaccagctctgctgatttgaaatttagattttttaaattatgtactggggacaggtttttgtcgctttacattgcttcctagtttacagcatgatgcaaatgattttctaacttagtgttaggagaaattattttccatctttaacctcttagttgtctaagagttaaatattactgaatttcagacgttcaaattgatcatcacaaatcctttaaaacaattacctaaaagaaaccaaaaatcctgccttctttgtgggggaggggggagagaggggaaggaaatggaacaagttgtgtttgtgttagcatgtgggtgatgtaaacttcaaattgggagatgttccgacccccactcccatataagcattcaatcagtgtaacttgcaaaatgcataaacatccggacagtttgaatttatagtgttgatggaagaaatcatttttaatgtgtactgtaaaacttgaaatactcaggagctgagtgagtatgtttgttgctacttacaatcccgacctgctagtcccagtagttttgttttaacatggtctttttcaactttgtttcctgtttaactacagatgacttctgttgtagactcacaagtttaactgttgtattataacacccttacatgtcaacggtgtggttatgacctttatttatataaaaaccaaatatttagtcaatttaccgtgtcttaatttaatctt</sbol:elements>
    <sbol:displayId>Exported_seq</sbol:displayId>
  </sbol:Sequence>
</rdf:RDF>
